jupinx/__init__.py
jupinx/cmd/__init__.py
jupinx/cmd/build.py
jupinx/cmd/quickstart.py
jupinx/templates/quickstart/Makefile_t
jupinx/templates/quickstart/conf.py_t
jupinx/templates/quickstart/demo_notebook.rst_t
jupinx/templates/quickstart/master_doc.rst_t
jupinx/templates/quickstart/_static/fill_demo1.png
jupinx/theme/minimal/README.md
jupinx/theme/minimal/static/css/base.css
jupinx/theme/minimal/static/img/code-block-fade.png
jupinx/theme/minimal/static/js/base.js
jupinx/theme/minimal/templates/error_report_template.html
jupinx/theme/minimal/templates/html.tpl
jupinx/theme/minimal/templates/latex.tpl
jupinx/util/__init__.py
jupinx/util/template.py
jupinx-0.2.3.dist-info/METADATA
jupinx-0.2.3.dist-info/WHEEL
jupinx-0.2.3.dist-info/entry_points.txt
jupinx-0.2.3.dist-info/top_level.txt
jupinx-0.2.3.dist-info/RECORD
